binance_futures/__init__.py
binance_futures/binance_futures.py
binance_future-4.0.dist-info/LICENSE
binance_future-4.0.dist-info/METADATA
binance_future-4.0.dist-info/WHEEL
binance_future-4.0.dist-info/top_level.txt
binance_future-4.0.dist-info/RECORD
