Metadata-Version: 2.1
Name: binance-future
Version: 4.0
Summary: Binance Futures API
Home-page: UNKNOWN
Author: Philippe Remy
License: MIT
Platform: UNKNOWN
Requires-Dist: attrs
Requires-Dist: unicorn-binance-websocket-api
